{
	"config": {
		"abort": {
			"already_configured": "[%key:common::config_flow::abort::already_configured_device%]",
			"cannot_identify": "Unable to determine a unique ID for this device. Please check your device and network configuration.",
			"no_devices_found": "[%key:common::config_flow::abort::no_devices_found%]",
			"single_instance_allowed": "[%key:common::config_flow::abort::single_instance_allowed%]"
		},
		"step": {
			"zeroconf_confirm": {
				"description": "You are setting up the Tewke device **{name}**{room_suffix}. Click Submit to continue.",
				"title": "Tewke device found"
			},
			"confirm_control_types": {
				"description": "Choose the Home Assistant platform type for each scene.\n\n**Light** (default) — the scene appears as a dimmable light entity.\n**Switch** — use this if you want to remove brightness control entirely.\n**Fan** — use this if you want brightness or speed control, but do not want the scene to appear as a light entity.",
				"title": "Configure scene types"
			},
			"placeholder": {
				"description": "Your Tewke device **{name}** is ready to be added to Home Assistant. Click Submit to complete the setup.",
				"title": "Final setup"
			}
		}
	},
	"issues": {
		"new_scenes_found": {
			"title": "New Scenes discovered",
			"description": "New Scenes have been discovered on your Tewke device {name}.\n\nPlease configure them to make them available in Home Assistant.",
			"fix_flow": {
				"step": {
					"init": {
						"title": "Configure new Tewke scenes",
						"description": "New scenes were found on your Tewke device {name}. Please assign a Home Assistant platform type for each new scene."
					}
				},
				"abort": {
					"no_new_scenes": "There are no new scenes pending configuration for your Tewke device {name}."
				}
			}
		}
	}
}
